bayesopt.pyd
bayesopt-0.3.data/data/LICENSE
bayesopt-0.3.dist-info/DESCRIPTION.rst
bayesopt-0.3.dist-info/METADATA
bayesopt-0.3.dist-info/RECORD
bayesopt-0.3.dist-info/WHEEL
bayesopt-0.3.dist-info/metadata.json
bayesopt-0.3.dist-info/top_level.txt
