Metadata-Version: 2.0
Name: bayesopt
Version: 0.3
Summary: BayesOpt is an efficient implementation of the Bayesian optimization methodology for nonlinear optimization, experimental design and hyperparameter tuning
Home-page: https://github.com/rmcantin/bayesopt
Author: Ruben Martinez-Cantin
Author-email: rmcantin@unizar.es
License: AGPL>=3.0
Platform: UNKNOWN
